odoo10_addon_server_environment-10.0.1.3.0-py2.7-nspkg.pth
odoo/addons/server_environment/README.rst
odoo/addons/server_environment/__init__.py
odoo/addons/server_environment/__manifest__.py
odoo/addons/server_environment/serv_config.py
odoo/addons/server_environment/serv_config.xml
odoo/addons/server_environment/system_info.py
odoo/addons/server_environment/i18n/am.po
odoo/addons/server_environment/i18n/ar.po
odoo/addons/server_environment/i18n/bg.po
odoo/addons/server_environment/i18n/bs.po
odoo/addons/server_environment/i18n/ca.po
odoo/addons/server_environment/i18n/cs.po
odoo/addons/server_environment/i18n/da.po
odoo/addons/server_environment/i18n/de.po
odoo/addons/server_environment/i18n/el_GR.po
odoo/addons/server_environment/i18n/en_GB.po
odoo/addons/server_environment/i18n/es.po
odoo/addons/server_environment/i18n/es_AR.po
odoo/addons/server_environment/i18n/es_CL.po
odoo/addons/server_environment/i18n/es_CO.po
odoo/addons/server_environment/i18n/es_CR.po
odoo/addons/server_environment/i18n/es_DO.po
odoo/addons/server_environment/i18n/es_EC.po
odoo/addons/server_environment/i18n/es_ES.po
odoo/addons/server_environment/i18n/es_MX.po
odoo/addons/server_environment/i18n/es_PE.po
odoo/addons/server_environment/i18n/es_PY.po
odoo/addons/server_environment/i18n/es_VE.po
odoo/addons/server_environment/i18n/et.po
odoo/addons/server_environment/i18n/eu.po
odoo/addons/server_environment/i18n/fa.po
odoo/addons/server_environment/i18n/fi.po
odoo/addons/server_environment/i18n/fr.po
odoo/addons/server_environment/i18n/fr_CA.po
odoo/addons/server_environment/i18n/fr_CH.po
odoo/addons/server_environment/i18n/gl.po
odoo/addons/server_environment/i18n/gl_ES.po
odoo/addons/server_environment/i18n/he.po
odoo/addons/server_environment/i18n/hr.po
odoo/addons/server_environment/i18n/hr_HR.po
odoo/addons/server_environment/i18n/hu.po
odoo/addons/server_environment/i18n/id.po
odoo/addons/server_environment/i18n/it.po
odoo10_addon_server_environment-10.0.1.3.0.dist-info/METADATA
odoo10_addon_server_environment-10.0.1.3.0.dist-info/RECORD
odoo10_addon_server_environment-10.0.1.3.0.dist-info/WHEEL
odoo10_addon_server_environment-10.0.1.3.0.dist-info/namespace_packages.txt
odoo10_addon_server_environment-10.0.1.3.0.dist-info/top_level.txt
